enrocrypt/__init__.py
enrocrypt/basic.py
enrocrypt/core.py
enrocrypt/encryption.py
enrocrypt/error.py
enrocrypt/hashing.py
enrocrypt/key.py
enrocrypt-1.1.4.dist-info/LICENSE
enrocrypt-1.1.4.dist-info/METADATA
enrocrypt-1.1.4.dist-info/WHEEL
enrocrypt-1.1.4.dist-info/top_level.txt
enrocrypt-1.1.4.dist-info/RECORD
