Metadata-Version: 2.1
Name: enrocrypt
Version: 1.1.4
Summary: This is a Python Module For Encryption, Hashing And Other stuff
Home-page: https://github.com/Morgan-Phoenix/EnroCrypt
Author: Morgan-Phoenix
Author-email: mikebrain61@gmail.com
License: UNKNOWN
Project-URL: Bug Tracker, https://github.com/Morgan-Phoenix/EnroCrypt/issues
Platform: UNKNOWN
Classifier: Programming Language :: Python :: 3
Classifier: License :: OSI Approved :: MIT License
Classifier: Operating System :: OS Independent
Requires-Python: >=3.6
License-File: LICENSE
Requires-Dist: cryptography
